bitmoro/__init__.py
bitmoro/message_api_dto.py
bitmoro/message_handler.py
bitmoro/message_scheduler.py
bitmoro/message_sender.py
bitmoro/otp_handler.py
bitmoro-0.1.1.dist-info/LICENSE.txt
bitmoro-0.1.1.dist-info/METADATA
bitmoro-0.1.1.dist-info/WHEEL
bitmoro-0.1.1.dist-info/top_level.txt
bitmoro-0.1.1.dist-info/RECORD
